[{"fixture":{"id":1048958,"referee":"T. Stieler","timezone":"UTC","date":"2023-10-28T13:30:00+00:00","timestamp":1698499800,"periods":{"first":1698499800,"second":1698503400},"venue":{"id":755,"name":"wohninvest WESERSTADION","city":"Bremen"},"status":{"long":"Match Finished","short":"FT","elapsed":90}},"league":{"id":78,"name":"Bundesliga","country":"Germany","logo":"https://media-4.api-sports.io/football/leagues/78.png","flag":"https://media-4.api-sports.io/flags/de.svg","season":2023,"round":"Regular Season - 9"},"teams":{"home":{"id":162,"name":"Werder Bremen","logo":"https://media-4.api-sports.io/football/teams/162.png","winner":true},"away":{"id":182,"name":"Union Berlin","logo":"https://media-4.api-sports.io/football/teams/182.png","winner":false}},"goals":{"home":2,"away":0},"score":{"halftime":{"home":1,"away":0},"fulltime":{"home":2,"away":0},"extratime":{"home":null,"away":null},"penalty":{"home":null,"away":null}},"events":[{"time":{"elapsed":38,"extra":null},"team":{"id":162,"name":"Werder Bremen","logo":"https://media-4.api-sports.io/football/teams/162.png"},"player":{"id":25403,"name":"R. Knoche"},"assist":{"id":null,"name":null},"type":"Goal","detail":"Own Goal","comments":null},{"time":{"elapsed":56,"extra":null},"team":{"id":182,"name":"Union Berlin","logo":"https://media-4.api-sports.io/football/teams/182.png"},"player":{"id":30422,"name":"Robin Gosens"},"assist":{"id":null,"name":null},"type":"Card","detail":"Yellow Card","comments":"Foul"},{"time":{"elapsed":60,"extra":null},"team":{"id":182,"name":"Union Berlin","logo":"https://media-4.api-sports.io/football/teams/182.png"},"player":{"id":25300,"name":"Rani Khedira"},"assist":{"id":null,"name":null},"type":"Card","detail":"Red Card","comments":"Foul"},{"time":{"elapsed":60,"extra":null},"team":{"id":182,"name":"Union Berlin","logo":"https://media-4.api-sports.io/football/teams/182.png"},"player":{"id":50739,"name":"B. Aaronson"},"assist":{"id":43246,"name":"A. Laïdouni"},"type":"subst","detail":"Substitution 1","comments":null},{"time":{"elapsed":65,"extra":null},"team":{"id":182,"name":"Union Berlin","logo":"https://media-4.api-sports.io/football/teams/182.png"},"player":{"id":26249,"name":"J. Haberer"},"assist":{"id":1234,"name":"A. Král"},"type":"subst","detail":"Substitution 2","comments":null},{"time":{"elapsed":73,"extra":null},"team":{"id":162,"name":"Werder Bremen","logo":"https://media-4.api-sports.io/football/teams/162.png"},"player":{"id":15592,"name":"Jens Stage"},"assist":{"id":null,"name":null},"type":"Card","detail":"Yellow Card","comments":"Foul"},{"time":{"elapsed":75,"extra":null},"team":{"id":162,"name":"Werder Bremen","logo":"https://media-4.api-sports.io/football/teams/162.png"},"player":{"id":25464,"name":"M. Ducksch"},"assist":{"id":2821,"name":"M. Veljković"},"type":"Goal","detail":"Normal Goal","comments":null},{"time":{"elapsed":76,"extra":null},"team":{"id":162,"name":"Werder Bremen","logo":"https://media-4.api-sports.io/football/teams/162.png"},"player":{"id":716,"name":"L. Bittencourt"},"assist":{"id":38798,"name":"S. Lynen"},"type":"subst","detail":"Substitution 1","comments":null},{"time":{"elapsed":78,"extra":null},"team":{"id":182,"name":"Union Berlin","logo":"https://media-4.api-sports.io/football/teams/182.png"},"player":{"id":25192,"name":"K. Behrens"},"assist":{"id":15732,"name":"M. Kaufmann"},"type":"subst","detail":"Substitution 3","comments":null},{"time":{"elapsed":78,"extra":null},"team":{"id":182,"name":"Union Berlin","logo":"https://media-4.api-sports.io/football/teams/182.png"},"player":{"id":37938,"name":"S. Becker"},"assist":{"id":162946,"name":"B. Hollerbach"},"type":"subst","detail":"Substitution 4","comments":null},{"time":{"elapsed":78,"extra":null},"team":{"id":182,"name":"Union Berlin","logo":"https://media-4.api-sports.io/football/teams/182.png"},"player":{"id":30422,"name":"R. Gosens"},"assist":{"id":25404,"name":"J. Roussillon"},"type":"subst","detail":"Substitution 5","comments":null},{"time":{"elapsed":80,"extra":null},"team":{"id":182,"name":"Union Berlin","logo":"https://media-4.api-sports.io/football/teams/182.png"},"player":{"id":376,"name":"Diogo Leite"},"assist":{"id":null,"name":null},"type":"Card","detail":"Yellow Card","comments":"Foul"},{"time":{"elapsed":84,"extra":null},"team":{"id":162,"name":"Werder Bremen","logo":"https://media-4.api-sports.io/football/teams/162.png"},"player":{"id":25464,"name":"M. Ducksch"},"assist":{"id":158054,"name":"N. Woltemade"},"type":"subst","detail":"Substitution 2","comments":null},{"time":{"elapsed":85,"extra":null},"team":{"id":182,"name":"Union Berlin","logo":"https://media-4.api-sports.io/football/teams/182.png"},"player":{"id":162946,"name":"Benedict Hollerbach"},"assist":{"id":null,"name":null},"type":"Card","detail":"Yellow Card","comments":"Foul"},{"time":{"elapsed":89,"extra":null},"team":{"id":162,"name":"Werder Bremen","logo":"https://media-4.api-sports.io/football/teams/162.png"},"player":{"id":8673,"name":"O. Deman"},"assist":{"id":26319,"name":"F. Agu"},"type":"subst","detail":"Substitution 3","comments":null},{"time":{"elapsed":89,"extra":null},"team":{"id":162,"name":"Werder Bremen","logo":"https://media-4.api-sports.io/football/teams/162.png"},"player":{"id":7562,"name":"R. Schmid"},"assist":{"id":177807,"name":"J. Njinmah"},"type":"subst","detail":"Substitution 4","comments":null},{"time":{"elapsed":90,"extra":6},"team":{"id":182,"name":"Union Berlin","logo":"https://media-4.api-sports.io/football/teams/182.png"},"player":{"id":43246,"name":"Aissa Laïdouni"},"assist":{"id":null,"name":null},"type":"Card","detail":"Yellow Card","comments":"Foul"}],"lineups":[{"team":{"id":162,"name":"Werder Bremen","logo":"https://media-4.api-sports.io/football/teams/162.png","colors":{"player":{"primary":"048d79","number":"1b6253","border":"048d79"},"goalkeeper":{"primary":"ff3366","number":"000000","border":"ff3366"}}},"coach":{"id":1348,"name":"O. Werner","photo":"https://media-4.api-sports.io/football/coachs/1348.png"},"formation":"3-5-2","startXI":[{"player":{"id":7288,"name":"M. Zetterer","number":30,"pos":"G","grid":"1:1"}},{"player":{"id":2821,"name":"M. Veljković","number":13,"pos":"D","grid":"2:3"}},{"player":{"id":25314,"name":"M. Friedl","number":32,"pos":"D","grid":"2:2"}},{"player":{"id":15874,"name":"A. Jung","number":3,"pos":"D","grid":"2:1"}},{"player":{"id":973,"name":"M. Weiser","number":8,"pos":"M","grid":"3:5"}},{"player":{"id":7562,"name":"R. Schmid","number":20,"pos":"M","grid":"3:4"}},{"player":{"id":15592,"name":"J. Stage","number":6,"pos":"M","grid":"3:3"}},{"player":{"id":716,"name":"L. Bittencourt","number":10,"pos":"M","grid":"3:2"}},{"player":{"id":8673,"name":"O. Deman","number":2,"pos":"M","grid":"3:1"}},{"player":{"id":6011,"name":"R. Borré","number":19,"pos":"F","grid":"4:2"}},{"player":{"id":25464,"name":"M. Ducksch","number":7,"pos":"F","grid":"4:1"}}],"substitutes":[{"player":{"id":38798,"name":"S. Lynen","number":14,"pos":"M","grid":null}},{"player":{"id":158054,"name":"N. Woltemade","number":29,"pos":"F","grid":null}},{"player":{"id":26319,"name":"F. Agu","number":27,"pos":"D","grid":null}},{"player":{"id":177807,"name":"J. Njinmah","number":17,"pos":"F","grid":null}},{"player":{"id":3013,"name":"D. Kownacki","number":9,"pos":"F","grid":null}},{"player":{"id":177841,"name":"Dudu","number":38,"pos":"G","grid":null}},{"player":{"id":363638,"name":"L. Opitz","number":35,"pos":"F","grid":null}},{"player":{"id":25011,"name":"A. Pieper","number":5,"pos":"D","grid":null}},{"player":{"id":88008,"name":"C. Röcker","number":40,"pos":"D","grid":null}}]},{"team":{"id":182,"name":"Union Berlin","logo":"https://media-4.api-sports.io/football/teams/182.png","colors":{"player":{"primary":"f70018","number":"fffefd","border":"f70018"},"goalkeeper":{"primary":"66ff66","number":"000000","border":"66ff66"}}},"coach":{"id":1544,"name":"U. Fischer","photo":"https://media-4.api-sports.io/football/coachs/1544.png"},"formation":"3-5-2","startXI":[{"player":{"id":1798,"name":"F. Rønnow","number":1,"pos":"G","grid":"1:1"}},{"player":{"id":853,"name":"L. Bonucci","number":23,"pos":"D","grid":"2:3"}},{"player":{"id":25403,"name":"R. Knoche","number":31,"pos":"D","grid":"2:2"}},{"player":{"id":376,"name":"Diogo Leite","number":4,"pos":"D","grid":"2:1"}},{"player":{"id":24848,"name":"C. Trimmel","number":28,"pos":"M","grid":"3:5"}},{"player":{"id":50739,"name":"B. Aaronson","number":7,"pos":"M","grid":"3:4"}},{"player":{"id":25300,"name":"R. Khedira","number":8,"pos":"M","grid":"3:3"}},{"player":{"id":26249,"name":"J. Haberer","number":19,"pos":"M","grid":"3:2"}},{"player":{"id":30422,"name":"R. Gosens","number":6,"pos":"M","grid":"3:1"}},{"player":{"id":37938,"name":"S. Becker","number":27,"pos":"F","grid":"4:2"}},{"player":{"id":25192,"name":"K. Behrens","number":17,"pos":"F","grid":"4:1"}}],"substitutes":[{"player":{"id":43246,"name":"A. Laïdouni","number":20,"pos":"M","grid":null}},{"player":{"id":1234,"name":"A. Král","number":33,"pos":"M","grid":null}},{"player":{"id":15732,"name":"M. Kaufmann","number":9,"pos":"F","grid":null}},{"player":{"id":162946,"name":"B. Hollerbach","number":16,"pos":"F","grid":null}},{"player":{"id":25404,"name":"J. Roussillon","number":26,"pos":"D","grid":null}},{"player":{"id":664,"name":"L. Tousart","number":29,"pos":"M","grid":null}},{"player":{"id":989,"name":"K. Volland","number":10,"pos":"F","grid":null}},{"player":{"id":25147,"name":"P. Jaeckel","number":3,"pos":"D","grid":null}},{"player":{"id":26234,"name":"A. Schwolow","number":37,"pos":"G","grid":null}}]}],"statistics":[{"team":{"id":162,"name":"Werder Bremen","logo":"https://media-4.api-sports.io/football/teams/162.png"},"statistics":[{"type":"Shots on Goal","value":4},{"type":"Shots off Goal","value":4},{"type":"Total Shots","value":10},{"type":"Blocked Shots","value":2},{"type":"Shots insidebox","value":5},{"type":"Shots outsidebox","value":5},{"type":"Fouls","value":12},{"type":"Corner Kicks","value":3},{"type":"Offsides","value":3},{"type":"Ball Possession","value":"57%"},{"type":"Yellow Cards","value":1},{"type":"Red Cards","value":null},{"type":"Goalkeeper Saves","value":2},{"type":"Total passes","value":579},{"type":"Passes accurate","value":491},{"type":"Passes %","value":"85%"},{"type":"expected_goals","value":"0.78"}]},{"team":{"id":182,"name":"Union Berlin","logo":"https://media-4.api-sports.io/football/teams/182.png"},"statistics":[{"type":"Shots on Goal","value":2},{"type":"Shots off Goal","value":3},{"type":"Total Shots","value":7},{"type":"Blocked Shots","value":2},{"type":"Shots insidebox","value":5},{"type":"Shots outsidebox","value":2},{"type":"Fouls","value":14},{"type":"Corner Kicks","value":3},{"type":"Offsides","value":5},{"type":"Ball Possession","value":"43%"},{"type":"Yellow Cards","value":4},{"type":"Red Cards","value":1},{"type":"Goalkeeper Saves","value":3},{"type":"Total passes","value":431},{"type":"Passes accurate","value":338},{"type":"Passes %","value":"78%"},{"type":"expected_goals","value":"0.57"}]}],"players":[{"team":{"id":162,"name":"Werder Bremen","logo":"https://media-4.api-sports.io/football/teams/162.png","update":"2023-10-31T04:22:33+00:00"},"players":[{"player":{"id":7288,"name":"Michael Zetterer","photo":"https://media-4.api-sports.io/football/players/7288.png"},"statistics":[{"games":{"minutes":90,"number":30,"position":"G","rating":"7.7","captain":false,"substitute":false},"offsides":null,"shots":{"total":null,"on":null},"goals":{"total":null,"conceded":0,"assists":null,"saves":2},"passes":{"total":27,"key":null,"accuracy":"21"},"tackles":{"total":null,"blocks":null,"interceptions":null},"duels":{"total":1,"won":1},"dribbles":{"attempts":null,"success":null,"past":null},"fouls":{"drawn":1,"committed":null},"cards":{"yellow":0,"red":0},"penalty":{"won":null,"commited":null,"scored":0,"missed":0,"saved":0}}]},{"player":{"id":2821,"name":"Miloš Veljković","photo":"https://media-4.api-sports.io/football/players/2821.png"},"statistics":[{"games":{"minutes":90,"number":13,"position":"D","rating":"8","captain":false,"substitute":false},"offsides":null,"shots":{"total":null,"on":null},"goals":{"total":null,"conceded":0,"assists":1,"saves":null},"passes":{"total":81,"key":1,"accuracy":"70"},"tackles":{"total":null,"blocks":null,"interceptions":1},"duels":{"total":6,"won":5},"dribbles":{"attempts":1,"success":1,"past":null},"fouls":{"drawn":null,"committed":null},"cards":{"yellow":0,"red":0},"penalty":{"won":null,"commited":null,"scored":0,"missed":0,"saved":null}}]},{"player":{"id":25314,"name":"Marco Friedl","photo":"https://media-4.api-sports.io/football/players/25314.png"},"statistics":[{"games":{"minutes":90,"number":32,"position":"D","rating":"7.5","captain":true,"substitute":false},"offsides":null,"shots":{"total":null,"on":null},"goals":{"total":null,"conceded":0,"assists":null,"saves":null},"passes":{"total":63,"key":null,"accuracy":"58"},"tackles":{"total":null,"blocks":1,"interceptions":1},"duels":{"total":9,"won":6},"dribbles":{"attempts":null,"success":null,"past":null},"fouls":{"drawn":null,"committed":2},"cards":{"yellow":0,"red":0},"penalty":{"won":null,"commited":null,"scored":0,"missed":0,"saved":null}}]},{"player":{"id":15874,"name":"Anthony Jung","photo":"https://media-4.api-sports.io/football/players/15874.png"},"statistics":[{"games":{"minutes":90,"number":3,"position":"D","rating":"7.3","captain":false,"substitute":false},"offsides":null,"shots":{"total":null,"on":null},"goals":{"total":null,"conceded":0,"assists":null,"saves":null},"passes":{"total":98,"key":null,"accuracy":"89"},"tackles":{"total":null,"blocks":null,"interceptions":1},"duels":{"total":4,"won":null},"dribbles":{"attempts":null,"success":null,"past":1},"fouls":{"drawn":null,"committed":null},"cards":{"yellow":0,"red":0},"penalty":{"won":null,"commited":null,"scored":0,"missed":0,"saved":null}}]},{"player":{"id":973,"name":"Mitchell Weiser","photo":"https://media-4.api-sports.io/football/players/973.png"},"statistics":[{"games":{"minutes":90,"number":8,"position":"M","rating":"6.7","captain":false,"substitute":false},"offsides":null,"shots":{"total":null,"on":null},"goals":{"total":null,"conceded":0,"assists":null,"saves":null},"passes":{"total":47,"key":null,"accuracy":"36"},"tackles":{"total":null,"blocks":null,"interceptions":null},"duels":{"total":8,"won":3},"dribbles":{"attempts":null,"success":null,"past":1},"fouls":{"drawn":1,"committed":null},"cards":{"yellow":0,"red":0},"penalty":{"won":null,"commited":null,"scored":0,"missed":0,"saved":null}}]},{"player":{"id":7562,"name":"Romano Schmid","photo":"https://media-4.api-sports.io/football/players/7562.png"},"statistics":[{"games":{"minutes":89,"number":20,"position":"M","rating":"6.9","captain":false,"substitute":false},"offsides":null,"shots":{"total":2,"on":1},"goals":{"total":null,"conceded":0,"assists":null,"saves":null},"passes":{"total":35,"key":1,"accuracy":"29"},"tackles":{"total":null,"blocks":null,"interceptions":null},"duels":{"total":12,"won":6},"dribbles":{"attempts":4,"success":1,"past":1},"fouls":{"drawn":3,"committed":null},"cards":{"yellow":0,"red":0},"penalty":{"won":null,"commited":null,"scored":0,"missed":0,"saved":null}}]},{"player":{"id":15592,"name":"Jens Stage","photo":"https://media-4.api-sports.io/football/players/15592.png"},"statistics":[{"games":{"minutes":90,"number":6,"position":"M","rating":"6.9","captain":false,"substitute":false},"offsides":null,"shots":{"total":null,"on":null},"goals":{"total":null,"conceded":0,"assists":null,"saves":null},"passes":{"total":51,"key":2,"accuracy":"43"},"tackles":{"total":2,"blocks":1,"interceptions":null},"duels":{"total":11,"won":3},"dribbles":{"attempts":null,"success":null,"past":null},"fouls":{"drawn":null,"committed":5},"cards":{"yellow":1,"red":0},"penalty":{"won":null,"commited":null,"scored":0,"missed":0,"saved":null}}]},{"player":{"id":716,"name":"Leonardo Bittencourt","photo":"https://media-4.api-sports.io/football/players/716.png"},"statistics":[{"games":{"minutes":76,"number":10,"position":"M","rating":"6.9","captain":false,"substitute":false},"offsides":null,"shots":{"total":2,"on":null},"goals":{"total":null,"conceded":0,"assists":null,"saves":null},"passes":{"total":45,"key":null,"accuracy":"38"},"tackles":{"total":null,"blocks":null,"interceptions":1},"duels":{"total":9,"won":3},"dribbles":{"attempts":1,"success":null,"past":2},"fouls":{"drawn":3,"committed":2},"cards":{"yellow":0,"red":0},"penalty":{"won":null,"commited":null,"scored":0,"missed":0,"saved":null}}]},{"player":{"id":8673,"name":"Olivier Deman","photo":"https://media-4.api-sports.io/football/players/8673.png"},"statistics":[{"games":{"minutes":89,"number":2,"position":"M","rating":"7.2","captain":false,"substitute":false},"offsides":null,"shots":{"total":null,"on":null},"goals":{"total":null,"conceded":0,"assists":null,"saves":null},"passes":{"total":52,"key":1,"accuracy":"47"},"tackles":{"total":4,"blocks":null,"interceptions":null},"duels":{"total":8,"won":5},"dribbles":{"attempts":1,"success":null,"past":1},"fouls":{"drawn":1,"committed":1},"cards":{"yellow":0,"red":0},"penalty":{"won":null,"commited":null,"scored":0,"missed":0,"saved":null}}]},{"player":{"id":6011,"name":"Rafael Santos Borré","photo":"https://media-4.api-sports.io/football/players/6011.png"},"statistics":[{"games":{"minutes":90,"number":19,"position":"F","rating":"6.6","captain":false,"substitute":false},"offsides":1,"shots":{"total":null,"on":null},"goals":{"total":null,"conceded":0,"assists":null,"saves":null},"passes":{"total":26,"key":null,"accuracy":"22"},"tackles":{"total":1,"blocks":null,"interceptions":null},"duels":{"total":9,"won":6},"dribbles":{"attempts":1,"success":1,"past":1},"fouls":{"drawn":2,"committed":null},"cards":{"yellow":0,"red":0},"penalty":{"won":null,"commited":null,"scored":0,"missed":0,"saved":null}}]},{"player":{"id":25464,"name":"Marvin Ducksch","photo":"https://media-4.api-sports.io/football/players/25464.png"},"statistics":[{"games":{"minutes":84,"number":7,"position":"F","rating":"7.6","captain":false,"substitute":false},"offsides":2,"shots":{"total":2,"on":1},"goals":{"total":1,"conceded":0,"assists":null,"saves":null},"passes":{"total":25,"key":1,"accuracy":"16"},"tackles":{"total":null,"blocks":null,"interceptions":null},"duels":{"total":6,"won":3},"dribbles":{"attempts":4,"success":2,"past":null},"fouls":{"drawn":1,"committed":null},"cards":{"yellow":0,"red":0},"penalty":{"won":null,"commited":null,"scored":0,"missed":0,"saved":null}}]},{"player":{"id":38798,"name":"Senne Lynen","photo":"https://media-4.api-sports.io/football/players/38798.png"},"statistics":[{"games":{"minutes":14,"number":14,"position":"M","rating":"6.9","captain":false,"substitute":true},"offsides":null,"shots":{"total":1,"on":1},"goals":{"total":null,"conceded":0,"assists":null,"saves":null},"passes":{"total":12,"key":1,"accuracy":"9"},"tackles":{"total":1,"blocks":null,"interceptions":1},"duels":{"total":4,"won":1},"dribbles":{"attempts":null,"success":null,"past":1},"fouls":{"drawn":null,"committed":1},"cards":{"yellow":0,"red":0},"penalty":{"won":null,"commited":null,"scored":0,"missed":0,"saved":null}}]},{"player":{"id":158054,"name":"Nick Woltemade","photo":"https://media-4.api-sports.io/football/players/158054.png"},"statistics":[{"games":{"minutes":14,"number":29,"position":"F","rating":"6.3","captain":false,"substitute":true},"offsides":null,"shots":{"total":null,"on":null},"goals":{"total":null,"conceded":0,"assists":null,"saves":null},"passes":{"total":5,"key":null,"accuracy":"4"},"tackles":{"total":null,"blocks":null,"interceptions":null},"duels":{"total":4,"won":1},"dribbles":{"attempts":null,"success":null,"past":1},"fouls":{"drawn":1,"committed":1},"cards":{"yellow":0,"red":0},"penalty":{"won":null,"commited":null,"scored":0,"missed":0,"saved":null}}]},{"player":{"id":26319,"name":"Felix Agu","photo":"https://media-4.api-sports.io/football/players/26319.png"},"statistics":[{"games":{"minutes":9,"number":27,"position":"D","rating":"6.7","captain":false,"substitute":true},"offsides":null,"shots":{"total":null,"on":null},"goals":{"total":null,"conceded":0,"assists":null,"saves":null},"passes":{"total":11,"key":1,"accuracy":"9"},"tackles":{"total":null,"blocks":null,"interceptions":null},"duels":{"total":null,"won":null},"dribbles":{"attempts":null,"success":null,"past":null},"fouls":{"drawn":null,"committed":null},"cards":{"yellow":0,"red":0},"penalty":{"won":null,"commited":null,"scored":0,"missed":0,"saved":null}}]},{"player":{"id":177807,"name":"Justin Njinmah","photo":"https://media-4.api-sports.io/football/players/177807.png"},"statistics":[{"games":{"minutes":10,"number":17,"position":"F","rating":"7","captain":false,"substitute":true},"offsides":null,"shots":{"total":1,"on":1},"goals":{"total":null,"conceded":0,"assists":null,"saves":null},"passes":{"total":1,"key":null,"accuracy":null},"tackles":{"total":null,"blocks":null,"interceptions":null},"duels":{"total":1,"won":1},"dribbles":{"attempts":null,"success":null,"past":null},"fouls":{"drawn":null,"committed":null},"cards":{"yellow":0,"red":0},"penalty":{"won":null,"commited":null,"scored":0,"missed":0,"saved":null}}]},{"player":{"id":177841,"name":"Eduardo Dos Santos Haesler","photo":"https://media-4.api-sports.io/football/players/177841.png"},"statistics":[{"games":{"minutes":null,"number":38,"position":"G","rating":null,"captain":false,"substitute":true},"offsides":null,"shots":{"total":null,"on":null},"goals":{"total":null,"conceded":0,"assists":null,"saves":null},"passes":{"total":null,"key":null,"accuracy":null},"tackles":{"total":null,"blocks":null,"interceptions":null},"duels":{"total":null,"won":null},"dribbles":{"attempts":null,"success":null,"past":null},"fouls":{"drawn":null,"committed":null},"cards":{"yellow":0,"red":0},"penalty":{"won":null,"commited":null,"scored":0,"missed":0,"saved":null}}]},{"player":{"id":88008,"name":"Cimo Röcker","photo":"https://media-4.api-sports.io/football/players/88008.png"},"statistics":[{"games":{"minutes":null,"number":40,"position":"D","rating":null,"captain":false,"substitute":true},"offsides":null,"shots":{"total":null,"on":null},"goals":{"total":null,"conceded":0,"assists":null,"saves":null},"passes":{"total":null,"key":null,"accuracy":null},"tackles":{"total":null,"blocks":null,"interceptions":null},"duels":{"total":null,"won":null},"dribbles":{"attempts":null,"success":null,"past":null},"fouls":{"drawn":null,"committed":null},"cards":{"yellow":0,"red":0},"penalty":{"won":null,"commited":null,"scored":0,"missed":0,"saved":null}}]},{"player":{"id":25011,"name":"Amos Pieper","photo":"https://media-4.api-sports.io/football/players/25011.png"},"statistics":[{"games":{"minutes":null,"number":5,"position":"D","rating":null,"captain":false,"substitute":true},"offsides":null,"shots":{"total":null,"on":null},"goals":{"total":null,"conceded":0,"assists":null,"saves":null},"passes":{"total":null,"key":null,"accuracy":null},"tackles":{"total":null,"blocks":null,"interceptions":null},"duels":{"total":null,"won":null},"dribbles":{"attempts":null,"success":null,"past":null},"fouls":{"drawn":null,"committed":null},"cards":{"yellow":0,"red":0},"penalty":{"won":null,"commited":null,"scored":0,"missed":0,"saved":null}}]},{"player":{"id":3013,"name":"Dawid Kownacki","photo":"https://media-4.api-sports.io/football/players/3013.png"},"statistics":[{"games":{"minutes":null,"number":9,"position":"F","rating":null,"captain":false,"substitute":true},"offsides":null,"shots":{"total":null,"on":null},"goals":{"total":null,"conceded":0,"assists":null,"saves":null},"passes":{"total":null,"key":null,"accuracy":null},"tackles":{"total":null,"blocks":null,"interceptions":null},"duels":{"total":null,"won":null},"dribbles":{"attempts":null,"success":null,"past":null},"fouls":{"drawn":null,"committed":null},"cards":{"yellow":0,"red":0},"penalty":{"won":null,"commited":null,"scored":0,"missed":0,"saved":null}}]},{"player":{"id":363638,"name":"Leon Opitz","photo":"https://media-4.api-sports.io/football/players/363638.png"},"statistics":[{"games":{"minutes":null,"number":35,"position":"F","rating":null,"captain":false,"substitute":true},"offsides":null,"shots":{"total":null,"on":null},"goals":{"total":null,"conceded":0,"assists":null,"saves":null},"passes":{"total":null,"key":null,"accuracy":null},"tackles":{"total":null,"blocks":null,"interceptions":null},"duels":{"total":null,"won":null},"dribbles":{"attempts":null,"success":null,"past":null},"fouls":{"drawn":null,"committed":null},"cards":{"yellow":0,"red":0},"penalty":{"won":null,"commited":null,"scored":0,"missed":0,"saved":null}}]}]},{"team":{"id":182,"name":"Union Berlin","logo":"https://media-4.api-sports.io/football/teams/182.png","update":"2023-10-31T04:22:33+00:00"},"players":[{"player":{"id":1798,"name":"Frederik Rønnow","photo":"https://media-4.api-sports.io/football/players/1798.png"},"statistics":[{"games":{"minutes":90,"number":1,"position":"G","rating":"6.2","captain":false,"substitute":false},"offsides":null,"shots":{"total":null,"on":null},"goals":{"total":null,"conceded":2,"assists":null,"saves":3},"passes":{"total":27,"key":null,"accuracy":"18"},"tackles":{"total":null,"blocks":null,"interceptions":null},"duels":{"total":null,"won":null},"dribbles":{"attempts":null,"success":null,"past":null},"fouls":{"drawn":null,"committed":null},"cards":{"yellow":0,"red":0},"penalty":{"won":null,"commited":null,"scored":0,"missed":0,"saved":0}}]},{"player":{"id":853,"name":"Leonardo Bonucci","photo":"https://media-4.api-sports.io/football/players/853.png"},"statistics":[{"games":{"minutes":90,"number":23,"position":"D","rating":"6.9","captain":false,"substitute":false},"offsides":null,"shots":{"total":null,"on":null},"goals":{"total":null,"conceded":0,"assists":null,"saves":null},"passes":{"total":54,"key":null,"accuracy":"39"},"tackles":{"total":2,"blocks":1,"interceptions":null},"duels":{"total":5,"won":4},"dribbles":{"attempts":1,"success":1,"past":null},"fouls":{"drawn":null,"committed":null},"cards":{"yellow":0,"red":0},"penalty":{"won":null,"commited":null,"scored":0,"missed":0,"saved":null}}]},{"player":{"id":25403,"name":"Robin Knoche","photo":"https://media-4.api-sports.io/football/players/25403.png"},"statistics":[{"games":{"minutes":90,"number":31,"position":"D","rating":"6.5","captain":false,"substitute":false},"offsides":null,"shots":{"total":null,"on":null},"goals":{"total":null,"conceded":0,"assists":null,"saves":null},"passes":{"total":55,"key":null,"accuracy":"49"},"tackles":{"total":3,"blocks":null,"interceptions":null},"duels":{"total":5,"won":3},"dribbles":{"attempts":null,"success":null,"past":1},"fouls":{"drawn":null,"committed":1},"cards":{"yellow":0,"red":0},"penalty":{"won":null,"commited":null,"scored":0,"missed":0,"saved":null}}]},{"player":{"id":376,"name":"Diogo Leite","photo":"https://media-4.api-sports.io/football/players/376.png"},"statistics":[{"games":{"minutes":90,"number":4,"position":"D","rating":"6.9","captain":false,"substitute":false},"offsides":null,"shots":{"total":null,"on":null},"goals":{"total":null,"conceded":0,"assists":null,"saves":null},"passes":{"total":62,"key":null,"accuracy":"51"},"tackles":{"total":4,"blocks":1,"interceptions":1},"duels":{"total":9,"won":5},"dribbles":{"attempts":null,"success":null,"past":1},"fouls":{"drawn":1,"committed":2},"cards":{"yellow":1,"red":0},"penalty":{"won":null,"commited":null,"scored":0,"missed":0,"saved":null}}]},{"player":{"id":24848,"name":"Christopher Trimmel","photo":"https://media-4.api-sports.io/football/players/24848.png"},"statistics":[{"games":{"minutes":90,"number":28,"position":"M","rating":"6.9","captain":true,"substitute":false},"offsides":null,"shots":{"total":1,"on":1},"goals":{"total":null,"conceded":0,"assists":null,"saves":null},"passes":{"total":33,"key":2,"accuracy":"20"},"tackles":{"total":null,"blocks":null,"interceptions":null},"duels":{"total":2,"won":1},"dribbles":{"attempts":1,"success":null,"past":null},"fouls":{"drawn":null,"committed":null},"cards":{"yellow":0,"red":0},"penalty":{"won":null,"commited":null,"scored":0,"missed":0,"saved":null}}]},{"player":{"id":50739,"name":"Brenden Aaronson","photo":"https://media-4.api-sports.io/football/players/50739.png"},"statistics":[{"games":{"minutes":60,"number":7,"position":"M","rating":"6.3","captain":false,"substitute":false},"offsides":null,"shots":{"total":null,"on":null},"goals":{"total":null,"conceded":0,"assists":null,"saves":null},"passes":{"total":11,"key":null,"accuracy":"10"},"tackles":{"total":null,"blocks":null,"interceptions":null},"duels":{"total":7,"won":2},"dribbles":{"attempts":3,"success":1,"past":null},"fouls":{"drawn":1,"committed":1},"cards":{"yellow":0,"red":0},"penalty":{"won":null,"commited":null,"scored":0,"missed":0,"saved":null}}]},{"player":{"id":25300,"name":"Rani Khedira","photo":"https://media-4.api-sports.io/football/players/25300.png"},"statistics":[{"games":{"minutes":60,"number":8,"position":"M","rating":"5.9","captain":false,"substitute":false},"offsides":null,"shots":{"total":null,"on":null},"goals":{"total":null,"conceded":0,"assists":null,"saves":null},"passes":{"total":38,"key":null,"accuracy":"28"},"tackles":{"total":2,"blocks":null,"interceptions":null},"duels":{"total":7,"won":4},"dribbles":{"attempts":null,"success":null,"past":1},"fouls":{"drawn":2,"committed":1},"cards":{"yellow":0,"red":1},"penalty":{"won":null,"commited":null,"scored":0,"missed":0,"saved":null}}]},{"player":{"id":26249,"name":"Janik Haberer","photo":"https://media-4.api-sports.io/football/players/26249.png"},"statistics":[{"games":{"minutes":65,"number":19,"position":"M","rating":"6.6","captain":false,"substitute":false},"offsides":1,"shots":{"total":1,"on":null},"goals":{"total":null,"conceded":0,"assists":null,"saves":null},"passes":{"total":29,"key":null,"accuracy":"24"},"tackles":{"total":null,"blocks":null,"interceptions":null},"duels":{"total":4,"won":1},"dribbles":{"attempts":1,"success":1,"past":null},"fouls":{"drawn":null,"committed":1},"cards":{"yellow":0,"red":0},"penalty":{"won":null,"commited":null,"scored":0,"missed":0,"saved":null}}]},{"player":{"id":30422,"name":"Robin Gosens","photo":"https://media-4.api-sports.io/football/players/30422.png"},"statistics":[{"games":{"minutes":78,"number":6,"position":"M","rating":"6.9","captain":false,"substitute":false},"offsides":1,"shots":{"total":1,"on":null},"goals":{"total":null,"conceded":0,"assists":null,"saves":null},"passes":{"total":34,"key":1,"accuracy":"30"},"tackles":{"total":2,"blocks":null,"interceptions":null},"duels":{"total":8,"won":5},"dribbles":{"attempts":null,"success":null,"past":null},"fouls":{"drawn":1,"committed":2},"cards":{"yellow":1,"red":0},"penalty":{"won":null,"commited":null,"scored":0,"missed":0,"saved":null}}]},{"player":{"id":37938,"name":"Sheraldo Becker","photo":"https://media-4.api-sports.io/football/players/37938.png"},"statistics":[{"games":{"minutes":78,"number":27,"position":"F","rating":"7.2","captain":false,"substitute":false},"offsides":1,"shots":{"total":null,"on":null},"goals":{"total":null,"conceded":0,"assists":null,"saves":null},"passes":{"total":27,"key":1,"accuracy":"20"},"tackles":{"total":1,"blocks":null,"interceptions":null},"duels":{"total":8,"won":4},"dribbles":{"attempts":3,"success":3,"past":1},"fouls":{"drawn":null,"committed":2},"cards":{"yellow":0,"red":0},"penalty":{"won":null,"commited":null,"scored":0,"missed":0,"saved":null}}]},{"player":{"id":25192,"name":"Kevin Behrens","photo":"https://media-4.api-sports.io/football/players/25192.png"},"statistics":[{"games":{"minutes":78,"number":17,"position":"F","rating":"7.2","captain":false,"substitute":false},"offsides":2,"shots":{"total":1,"on":null},"goals":{"total":null,"conceded":0,"assists":null,"saves":null},"passes":{"total":28,"key":null,"accuracy":"20"},"tackles":{"total":null,"blocks":null,"interceptions":null},"duels":{"total":20,"won":11},"dribbles":{"attempts":1,"success":1,"past":null},"fouls":{"drawn":3,"committed":1},"cards":{"yellow":0,"red":0},"penalty":{"won":null,"commited":null,"scored":0,"missed":0,"saved":null}}]},{"player":{"id":43246,"name":"Aissa Laïdouni","photo":"https://media-4.api-sports.io/football/players/43246.png"},"statistics":[{"games":{"minutes":30,"number":20,"position":"M","rating":"7","captain":false,"substitute":true},"offsides":null,"shots":{"total":1,"on":1},"goals":{"total":null,"conceded":0,"assists":null,"saves":null},"passes":{"total":11,"key":null,"accuracy":"8"},"tackles":{"total":1,"blocks":null,"interceptions":null},"duels":{"total":10,"won":6},"dribbles":{"attempts":1,"success":1,"past":null},"fouls":{"drawn":3,"committed":2},"cards":{"yellow":1,"red":0},"penalty":{"won":null,"commited":null,"scored":0,"missed":0,"saved":null}}]},{"player":{"id":1234,"name":"Alex Král","photo":"https://media-4.api-sports.io/football/players/1234.png"},"statistics":[{"games":{"minutes":25,"number":33,"position":"M","rating":"6.2","captain":false,"substitute":true},"offsides":null,"shots":{"total":null,"on":null},"goals":{"total":null,"conceded":0,"assists":null,"saves":null},"passes":{"total":11,"key":null,"accuracy":"11"},"tackles":{"total":null,"blocks":null,"interceptions":1},"duels":{"total":2,"won":null},"dribbles":{"attempts":1,"success":null,"past":null},"fouls":{"drawn":null,"committed":null},"cards":{"yellow":0,"red":0},"penalty":{"won":null,"commited":null,"scored":0,"missed":0,"saved":null}}]},{"player":{"id":25404,"name":"Jérôme Roussillon","photo":"https://media-4.api-sports.io/football/players/25404.png"},"statistics":[{"games":{"minutes":12,"number":26,"position":"D","rating":"6.3","captain":false,"substitute":true},"offsides":null,"shots":{"total":null,"on":null},"goals":{"total":null,"conceded":0,"assists":null,"saves":null},"passes":{"total":4,"key":null,"accuracy":"4"},"tackles":{"total":null,"blocks":null,"interceptions":null},"duels":{"total":null,"won":null},"dribbles":{"attempts":null,"success":null,"past":null},"fouls":{"drawn":null,"committed":null},"cards":{"yellow":0,"red":0},"penalty":{"won":null,"commited":null,"scored":0,"missed":0,"saved":null}}]},{"player":{"id":15732,"name":"Mikkel Kaufmann","photo":"https://media-4.api-sports.io/football/players/15732.png"},"statistics":[{"games":{"minutes":12,"number":9,"position":"F","rating":"6.7","captain":false,"substitute":true},"offsides":null,"shots":{"total":null,"on":null},"goals":{"total":null,"conceded":0,"assists":null,"saves":null},"passes":{"total":3,"key":null,"accuracy":"3"},"tackles":{"total":null,"blocks":null,"interceptions":null},"duels":{"total":2,"won":1},"dribbles":{"attempts":null,"success":null,"past":null},"fouls":{"drawn":1,"committed":null},"cards":{"yellow":0,"red":0},"penalty":{"won":null,"commited":null,"scored":0,"missed":0,"saved":null}}]},{"player":{"id":162946,"name":"Benedict Hollerbach","photo":"https://media-4.api-sports.io/football/players/162946.png"},"statistics":[{"games":{"minutes":12,"number":16,"position":"F","rating":"6.9","captain":false,"substitute":true},"offsides":null,"shots":{"total":null,"on":null},"goals":{"total":null,"conceded":0,"assists":null,"saves":null},"passes":{"total":4,"key":1,"accuracy":"3"},"tackles":{"total":null,"blocks":null,"interceptions":null},"duels":{"total":3,"won":1},"dribbles":{"attempts":1,"success":1,"past":1},"fouls":{"drawn":null,"committed":1},"cards":{"yellow":1,"red":0},"penalty":{"won":null,"commited":null,"scored":0,"missed":0,"saved":null}}]},{"player":{"id":26234,"name":"Alexander Schwolow","photo":"https://media-4.api-sports.io/football/players/26234.png"},"statistics":[{"games":{"minutes":null,"number":37,"position":"G","rating":null,"captain":false,"substitute":true},"offsides":null,"shots":{"total":null,"on":null},"goals":{"total":null,"conceded":0,"assists":null,"saves":null},"passes":{"total":null,"key":null,"accuracy":null},"tackles":{"total":null,"blocks":null,"interceptions":null},"duels":{"total":null,"won":null},"dribbles":{"attempts":null,"success":null,"past":null},"fouls":{"drawn":null,"committed":null},"cards":{"yellow":0,"red":0},"penalty":{"won":null,"commited":null,"scored":0,"missed":0,"saved":null}}]},{"player":{"id":25147,"name":"Paul Jaeckel","photo":"https://media-4.api-sports.io/football/players/25147.png"},"statistics":[{"games":{"minutes":null,"number":3,"position":"D","rating":null,"captain":false,"substitute":true},"offsides":null,"shots":{"total":null,"on":null},"goals":{"total":null,"conceded":0,"assists":null,"saves":null},"passes":{"total":null,"key":null,"accuracy":null},"tackles":{"total":null,"blocks":null,"interceptions":null},"duels":{"total":null,"won":null},"dribbles":{"attempts":null,"success":null,"past":null},"fouls":{"drawn":null,"committed":null},"cards":{"yellow":0,"red":0},"penalty":{"won":null,"commited":null,"scored":0,"missed":0,"saved":null}}]},{"player":{"id":664,"name":"Lucas Tousart","photo":"https://media-4.api-sports.io/football/players/664.png"},"statistics":[{"games":{"minutes":null,"number":29,"position":"M","rating":null,"captain":false,"substitute":true},"offsides":null,"shots":{"total":null,"on":null},"goals":{"total":null,"conceded":0,"assists":null,"saves":null},"passes":{"total":null,"key":null,"accuracy":null},"tackles":{"total":null,"blocks":null,"interceptions":null},"duels":{"total":null,"won":null},"dribbles":{"attempts":null,"success":null,"past":null},"fouls":{"drawn":null,"committed":null},"cards":{"yellow":0,"red":0},"penalty":{"won":null,"commited":null,"scored":0,"missed":0,"saved":null}}]},{"player":{"id":989,"name":"Kevin Volland","photo":"https://media-4.api-sports.io/football/players/989.png"},"statistics":[{"games":{"minutes":null,"number":10,"position":"F","rating":null,"captain":false,"substitute":true},"offsides":null,"shots":{"total":null,"on":null},"goals":{"total":null,"conceded":0,"assists":null,"saves":null},"passes":{"total":null,"key":null,"accuracy":null},"tackles":{"total":null,"blocks":null,"interceptions":null},"duels":{"total":null,"won":null},"dribbles":{"attempts":null,"success":null,"past":null},"fouls":{"drawn":null,"committed":null},"cards":{"yellow":0,"red":0},"penalty":{"won":null,"commited":null,"scored":0,"missed":0,"saved":null}}]}]}]}]