[{"fixture":{"id":1052311,"referee":"I. Pezzuto","timezone":"UTC","date":"2023-09-28T16:30:00+00:00","timestamp":1695918600,"periods":{"first":1695918600,"second":1695922200},"venue":{"id":12086,"name":"U-Power Stadium","city":"Monza"},"status":{"long":"Match Finished","short":"FT","elapsed":90}},"league":{"id":135,"name":"Serie A","country":"Italy","logo":"https://media-4.api-sports.io/football/leagues/135.png","flag":"https://media-4.api-sports.io/flags/it.svg","season":2023,"round":"Regular Season - 6"},"teams":{"home":{"id":1579,"name":"Monza","logo":"https://media-4.api-sports.io/football/teams/1579.png","winner":null},"away":{"id":500,"name":"Bologna","logo":"https://media-4.api-sports.io/football/teams/500.png","winner":null}},"goals":{"home":0,"away":0},"score":{"halftime":{"home":0,"away":0},"fulltime":{"home":0,"away":0},"extratime":{"home":null,"away":null},"penalty":{"home":null,"away":null}},"events":[{"time":{"elapsed":12,"extra":null},"team":{"id":500,"name":"Bologna","logo":"https://media-4.api-sports.io/football/teams/500.png"},"player":{"id":30488,"name":"Riccardo Orsolini"},"assist":{"id":null,"name":null},"type":"Card","detail":"Yellow Card","comments":"Foul"},{"time":{"elapsed":17,"extra":null},"team":{"id":1579,"name":"Monza","logo":"https://media-4.api-sports.io/football/teams/1579.png"},"player":{"id":30603,"name":"Dany Mota"},"assist":{"id":null,"name":null},"type":"Var","detail":"Goal cancelled","comments":null},{"time":{"elapsed":59,"extra":null},"team":{"id":500,"name":"Bologna","logo":"https://media-4.api-sports.io/football/teams/500.png"},"player":{"id":30488,"name":"R. Orsolini"},"assist":{"id":48648,"name":"D. Ndoye"},"type":"subst","detail":"Substitution 1","comments":null},{"time":{"elapsed":59,"extra":null},"team":{"id":500,"name":"Bologna","logo":"https://media-4.api-sports.io/football/teams/500.png"},"player":{"id":48079,"name":"J. Karlsson"},"assist":{"id":1417,"name":"A. Saelemaekers"},"type":"subst","detail":"Substitution 2","comments":null},{"time":{"elapsed":59,"extra":null},"team":{"id":500,"name":"Bologna","logo":"https://media-4.api-sports.io/football/teams/500.png"},"player":{"id":30498,"name":"L. De Silvestri"},"assist":{"id":341974,"name":"T. Corazza"},"type":"subst","detail":"Substitution 3","comments":null},{"time":{"elapsed":59,"extra":null},"team":{"id":500,"name":"Bologna","logo":"https://media-4.api-sports.io/football/teams/500.png"},"player":{"id":30553,"name":"C. Lykogiannis"},"assist":{"id":158710,"name":"V. Kristiansen"},"type":"subst","detail":"Substitution 4","comments":null},{"time":{"elapsed":63,"extra":null},"team":{"id":1579,"name":"Monza","logo":"https://media-4.api-sports.io/football/teams/1579.png"},"player":{"id":26828,"name":"G. Kyriakopoulos"},"assist":{"id":30708,"name":"S. Birindelli"},"type":"subst","detail":"Substitution 1","comments":null},{"time":{"elapsed":64,"extra":null},"team":{"id":1579,"name":"Monza","logo":"https://media-4.api-sports.io/football/teams/1579.png"},"player":{"id":30603,"name":"Dany Mota"},"assist":{"id":312985,"name":"S. Vignato"},"type":"subst","detail":"Substitution 2","comments":null},{"time":{"elapsed":67,"extra":null},"team":{"id":1579,"name":"Monza","logo":"https://media-4.api-sports.io/football/teams/1579.png"},"player":{"id":193270,"name":"A. Carboni"},"assist":{"id":46792,"name":"Pablo Marí"},"type":"subst","detail":"Substitution 3","comments":null},{"time":{"elapsed":70,"extra":null},"team":{"id":1579,"name":"Monza","logo":"https://media-4.api-sports.io/football/teams/1579.png"},"player":{"id":312985,"name":"Samuele Vignato"},"assist":{"id":null,"name":null},"type":"Card","detail":"Yellow Card","comments":"Foul"},{"time":{"elapsed":75,"extra":null},"team":{"id":500,"name":"Bologna","logo":"https://media-4.api-sports.io/football/teams/500.png"},"player":{"id":70100,"name":"J. Zirkzee"},"assist":{"id":38713,"name":"S. van Hooijdonk"},"type":"subst","detail":"Substitution 5","comments":null},{"time":{"elapsed":78,"extra":null},"team":{"id":1579,"name":"Monza","logo":"https://media-4.api-sports.io/football/teams/1579.png"},"player":{"id":30431,"name":"A. Colpani"},"assist":{"id":31024,"name":"José Machín"},"type":"subst","detail":"Substitution 4","comments":null},{"time":{"elapsed":78,"extra":null},"team":{"id":1579,"name":"Monza","logo":"https://media-4.api-sports.io/football/teams/1579.png"},"player":{"id":263481,"name":"L. Colombo"},"assist":{"id":9072,"name":"M. Marić"},"type":"subst","detail":"Substitution 5","comments":null},{"time":{"elapsed":80,"extra":null},"team":{"id":1579,"name":"Monza","logo":"https://media-4.api-sports.io/football/teams/1579.png"},"player":{"id":30708,"name":"Samuele Birindelli"},"assist":{"id":null,"name":null},"type":"Card","detail":"Yellow Card","comments":"Foul"},{"time":{"elapsed":85,"extra":null},"team":{"id":1579,"name":"Monza","logo":"https://media-4.api-sports.io/football/teams/1579.png"},"player":{"id":31532,"name":"Patrick Ciurria"},"assist":{"id":null,"name":null},"type":"Card","detail":"Yellow Card","comments":"Foul"},{"time":{"elapsed":86,"extra":null},"team":{"id":500,"name":"Bologna","logo":"https://media-4.api-sports.io/football/teams/500.png"},"player":{"id":1417,"name":"Alexis Saelemaekers"},"assist":{"id":null,"name":null},"type":"Card","detail":"Red Card","comments":"Argument"},{"time":{"elapsed":86,"extra":null},"team":{"id":500,"name":"Bologna","logo":"https://media-4.api-sports.io/football/teams/500.png"},"player":{"id":1417,"name":"Alexis Saelemaekers"},"assist":{"id":null,"name":null},"type":"Card","detail":"Yellow Card","comments":"Argument"},{"time":{"elapsed":86,"extra":null},"team":{"id":500,"name":"Bologna","logo":"https://media-4.api-sports.io/football/teams/500.png"},"player":{"id":1417,"name":"Alexis Saelemaekers"},"assist":{"id":null,"name":null},"type":"Card","detail":"Yellow Card","comments":"Argument"},{"time":{"elapsed":88,"extra":null},"team":{"id":1579,"name":"Monza","logo":"https://media-4.api-sports.io/football/teams/1579.png"},"player":{"id":203,"name":"Roberto Gagliardini"},"assist":{"id":null,"name":null},"type":"Card","detail":"Yellow Card","comments":"Foul"},{"time":{"elapsed":90,"extra":3},"team":{"id":1579,"name":"Monza","logo":"https://media-4.api-sports.io/football/teams/1579.png"},"player":{"id":46792,"name":"Pablo Marí"},"assist":{"id":null,"name":null},"type":"Card","detail":"Yellow Card","comments":"Argument"}],"lineups":[{"team":{"id":1579,"name":"Monza","logo":"https://media-4.api-sports.io/football/teams/1579.png","colors":{"player":{"primary":"fa0000","number":"ffffff","border":"fa0000"},"goalkeeper":{"primary":"ffffff","number":"000000","border":"ffffff"}}},"coach":{"id":18433,"name":"R. Palladino","photo":"https://media-4.api-sports.io/football/coachs/18433.png"},"formation":"3-4-3","startXI":[{"player":{"id":30670,"name":"M. Di Gregorio","number":16,"pos":"G","grid":"1:1"}},{"player":{"id":30501,"name":"A. Izzo","number":4,"pos":"D","grid":"2:3"}},{"player":{"id":30615,"name":"L. Caldirola","number":5,"pos":"D","grid":"2:2"}},{"player":{"id":193270,"name":"A. Carboni","number":44,"pos":"D","grid":"2:1"}},{"player":{"id":31532,"name":"P. Ciurria","number":84,"pos":"M","grid":"3:4"}},{"player":{"id":30436,"name":"M. Pessina","number":32,"pos":"M","grid":"3:3"}},{"player":{"id":203,"name":"R. Gagliardini","number":6,"pos":"M","grid":"3:2"}},{"player":{"id":26828,"name":"G. Kyriakopoulos","number":77,"pos":"M","grid":"3:1"}},{"player":{"id":30431,"name":"A. Colpani","number":28,"pos":"F","grid":"4:3"}},{"player":{"id":263481,"name":"L. Colombo","number":9,"pos":"F","grid":"4:2"}},{"player":{"id":30603,"name":"Dany Mota","number":47,"pos":"F","grid":"4:1"}}],"substitutes":[{"player":{"id":30708,"name":"S. Birindelli","number":19,"pos":"D","grid":null}},{"player":{"id":312985,"name":"S. Vignato","number":80,"pos":"F","grid":null}},{"player":{"id":46792,"name":"Pablo Marí","number":22,"pos":"D","grid":null}},{"player":{"id":31024,"name":"José Machín","number":7,"pos":"M","grid":null}},{"player":{"id":9072,"name":"M. Marić","number":24,"pos":"F","grid":null}},{"player":{"id":31678,"name":"J. Akpa Akpro","number":8,"pos":"M","grid":null}},{"player":{"id":341646,"name":"V. Carboni","number":21,"pos":"M","grid":null}},{"player":{"id":25911,"name":"G. Donati","number":2,"pos":"D","grid":null}},{"player":{"id":193,"name":"D. D'Ambrosio","number":33,"pos":"D","grid":null}},{"player":{"id":266813,"name":"W. Bondo","number":38,"pos":"M","grid":null}},{"player":{"id":286473,"name":"F. Carboni","number":11,"pos":"D","grid":null}},{"player":{"id":30768,"name":"Pedro Pereira","number":13,"pos":"D","grid":null}},{"player":{"id":162570,"name":"G. Cittadini","number":46,"pos":"D","grid":null}},{"player":{"id":30704,"name":"S. Gori","number":66,"pos":"G","grid":null}},{"player":{"id":129553,"name":"A. Sorrentino","number":23,"pos":"G","grid":null}}]},{"team":{"id":500,"name":"Bologna","logo":"https://media-4.api-sports.io/football/teams/500.png","colors":{"player":{"primary":"ffffff","number":"003163","border":"ffffff"},"goalkeeper":{"primary":"ff3333","number":"0000ff","border":"ff3333"}}},"coach":{"id":4842,"name":"T. Motta","photo":"https://media-4.api-sports.io/football/coachs/4842.png"},"formation":"4-2-3-1","startXI":[{"player":{"id":2998,"name":"Ł. Skorupski","number":28,"pos":"G","grid":"1:1"}},{"player":{"id":30498,"name":"L. De Silvestri","number":29,"pos":"D","grid":"2:4"}},{"player":{"id":37604,"name":"S. Beukema","number":31,"pos":"D","grid":"2:3"}},{"player":{"id":157052,"name":"R. Calafiori","number":33,"pos":"D","grid":"2:2"}},{"player":{"id":30553,"name":"C. Lykogiannis","number":22,"pos":"D","grid":"2:1"}},{"player":{"id":951,"name":"M. Aebischer","number":20,"pos":"M","grid":"3:2"}},{"player":{"id":319919,"name":"O. El Azzouzi","number":17,"pos":"M","grid":"3:1"}},{"player":{"id":30488,"name":"R. Orsolini","number":7,"pos":"M","grid":"4:3"}},{"player":{"id":44814,"name":"L. Ferguson","number":19,"pos":"M","grid":"4:2"}},{"player":{"id":48079,"name":"J. Karlsson","number":10,"pos":"M","grid":"4:1"}},{"player":{"id":70100,"name":"J. Zirkzee","number":9,"pos":"F","grid":"5:1"}}],"substitutes":[{"player":{"id":158710,"name":"V. Kristiansen","number":15,"pos":"M","grid":null}},{"player":{"id":341974,"name":"T. Corazza","number":16,"pos":"D","grid":null}},{"player":{"id":1417,"name":"A. Saelemaekers","number":56,"pos":"F","grid":null}},{"player":{"id":48648,"name":"D. Ndoye","number":11,"pos":"F","grid":null}},{"player":{"id":38713,"name":"S. van Hooijdonk","number":77,"pos":"F","grid":null}},{"player":{"id":2807,"name":"R. Freuler","number":8,"pos":"M","grid":null}},{"player":{"id":322630,"name":"G. Fabbian","number":80,"pos":"M","grid":null}},{"player":{"id":1322,"name":"N. Moro","number":6,"pos":"M","grid":null}},{"player":{"id":339180,"name":"N. Bagnolini","number":23,"pos":"G","grid":null}},{"player":{"id":31098,"name":"F. Ravaglia","number":34,"pos":"G","grid":null}},{"player":{"id":182280,"name":"K. Urbański","number":82,"pos":"M","grid":null}},{"player":{"id":30853,"name":"K. Bonifazi","number":14,"pos":"D","grid":null}}]}],"statistics":[{"team":{"id":1579,"name":"Monza","logo":"https://media-4.api-sports.io/football/teams/1579.png"},"statistics":[{"type":"Shots on Goal","value":3},{"type":"Shots off Goal","value":4},{"type":"Total Shots","value":10},{"type":"Blocked Shots","value":3},{"type":"Shots insidebox","value":5},{"type":"Shots outsidebox","value":5},{"type":"Fouls","value":9},{"type":"Corner Kicks","value":7},{"type":"Offsides","value":2},{"type":"Ball Possession","value":"48%"},{"type":"Yellow Cards","value":5},{"type":"Red Cards","value":null},{"type":"Goalkeeper Saves","value":5},{"type":"Total passes","value":462},{"type":"Passes accurate","value":391},{"type":"Passes %","value":"85%"},{"type":"expected_goals","value":"0.74"}]},{"team":{"id":500,"name":"Bologna","logo":"https://media-4.api-sports.io/football/teams/500.png"},"statistics":[{"type":"Shots on Goal","value":5},{"type":"Shots off Goal","value":null},{"type":"Total Shots","value":7},{"type":"Blocked Shots","value":2},{"type":"Shots insidebox","value":4},{"type":"Shots outsidebox","value":3},{"type":"Fouls","value":15},{"type":"Corner Kicks","value":5},{"type":"Offsides","value":2},{"type":"Ball Possession","value":"52%"},{"type":"Yellow Cards","value":3},{"type":"Red Cards","value":1},{"type":"Goalkeeper Saves","value":3},{"type":"Total passes","value":525},{"type":"Passes accurate","value":454},{"type":"Passes %","value":"86%"},{"type":"expected_goals","value":"0.58"}]}],"players":[{"team":{"id":1579,"name":"Monza","logo":"https://media-4.api-sports.io/football/teams/1579.png","update":"2023-10-10T04:05:11+00:00"},"players":[{"player":{"id":30670,"name":"Michele Di Gregorio","photo":"https://media-4.api-sports.io/football/players/30670.png"},"statistics":[{"games":{"minutes":90,"number":16,"position":"G","rating":"8","captain":false,"substitute":false},"offsides":null,"shots":{"total":null,"on":null},"goals":{"total":null,"conceded":0,"assists":null,"saves":5},"passes":{"total":23,"key":null,"accuracy":"15"},"tackles":{"total":null,"blocks":null,"interceptions":null},"duels":{"total":null,"won":null},"dribbles":{"attempts":null,"success":null,"past":null},"fouls":{"drawn":null,"committed":null},"cards":{"yellow":0,"red":0},"penalty":{"won":null,"commited":null,"scored":0,"missed":0,"saved":0}}]},{"player":{"id":30501,"name":"Armando Izzo","photo":"https://media-4.api-sports.io/football/players/30501.png"},"statistics":[{"games":{"minutes":90,"number":4,"position":"D","rating":"6.9","captain":false,"substitute":false},"offsides":null,"shots":{"total":null,"on":null},"goals":{"total":null,"conceded":0,"assists":null,"saves":null},"passes":{"total":71,"key":null,"accuracy":"64"},"tackles":{"total":1,"blocks":null,"interceptions":null},"duels":{"total":9,"won":3},"dribbles":{"attempts":null,"success":null,"past":4},"fouls":{"drawn":2,"committed":1},"cards":{"yellow":0,"red":0},"penalty":{"won":null,"commited":null,"scored":0,"missed":0,"saved":null}}]},{"player":{"id":30615,"name":"Luca Caldirola","photo":"https://media-4.api-sports.io/football/players/30615.png"},"statistics":[{"games":{"minutes":90,"number":5,"position":"D","rating":"7","captain":false,"substitute":false},"offsides":null,"shots":{"total":null,"on":null},"goals":{"total":null,"conceded":0,"assists":null,"saves":null},"passes":{"total":38,"key":null,"accuracy":"35"},"tackles":{"total":1,"blocks":null,"interceptions":3},"duels":{"total":5,"won":3},"dribbles":{"attempts":null,"success":null,"past":1},"fouls":{"drawn":2,"committed":null},"cards":{"yellow":0,"red":0},"penalty":{"won":null,"commited":null,"scored":0,"missed":0,"saved":null}}]},{"player":{"id":193270,"name":"Andrea Carboni","photo":"https://media-4.api-sports.io/football/players/193270.png"},"statistics":[{"games":{"minutes":67,"number":44,"position":"D","rating":"6.6","captain":false,"substitute":false},"offsides":null,"shots":{"total":null,"on":null},"goals":{"total":null,"conceded":0,"assists":null,"saves":null},"passes":{"total":42,"key":null,"accuracy":"37"},"tackles":{"total":1,"blocks":null,"interceptions":null},"duels":{"total":5,"won":3},"dribbles":{"attempts":null,"success":null,"past":1},"fouls":{"drawn":null,"committed":1},"cards":{"yellow":0,"red":0},"penalty":{"won":null,"commited":null,"scored":0,"missed":0,"saved":null}}]},{"player":{"id":31532,"name":"Patrick Ciurria","photo":"https://media-4.api-sports.io/football/players/31532.png"},"statistics":[{"games":{"minutes":90,"number":84,"position":"M","rating":"6.9","captain":false,"substitute":false},"offsides":null,"shots":{"total":null,"on":null},"goals":{"total":null,"conceded":0,"assists":null,"saves":null},"passes":{"total":38,"key":1,"accuracy":"32"},"tackles":{"total":null,"blocks":1,"interceptions":null},"duels":{"total":4,"won":1},"dribbles":{"attempts":2,"success":1,"past":null},"fouls":{"drawn":null,"committed":2},"cards":{"yellow":1,"red":0},"penalty":{"won":null,"commited":null,"scored":0,"missed":0,"saved":null}}]},{"player":{"id":30436,"name":"Matteo Pessina","photo":"https://media-4.api-sports.io/football/players/30436.png"},"statistics":[{"games":{"minutes":90,"number":32,"position":"M","rating":"7.5","captain":true,"substitute":false},"offsides":null,"shots":{"total":1,"on":1},"goals":{"total":null,"conceded":0,"assists":null,"saves":null},"passes":{"total":54,"key":null,"accuracy":"48"},"tackles":{"total":2,"blocks":1,"interceptions":null},"duels":{"total":10,"won":7},"dribbles":{"attempts":1,"success":1,"past":null},"fouls":{"drawn":3,"committed":null},"cards":{"yellow":0,"red":0},"penalty":{"won":null,"commited":null,"scored":0,"missed":0,"saved":null}}]},{"player":{"id":203,"name":"Roberto Gagliardini","photo":"https://media-4.api-sports.io/football/players/203.png"},"statistics":[{"games":{"minutes":90,"number":6,"position":"M","rating":"7","captain":false,"substitute":false},"offsides":null,"shots":{"total":null,"on":null},"goals":{"total":null,"conceded":0,"assists":null,"saves":null},"passes":{"total":45,"key":null,"accuracy":"41"},"tackles":{"total":2,"blocks":null,"interceptions":1},"duels":{"total":11,"won":6},"dribbles":{"attempts":3,"success":2,"past":null},"fouls":{"drawn":2,"committed":2},"cards":{"yellow":1,"red":0},"penalty":{"won":null,"commited":null,"scored":0,"missed":0,"saved":null}}]},{"player":{"id":26828,"name":"Georgios Kyriakopoulos","photo":"https://media-4.api-sports.io/football/players/26828.png"},"statistics":[{"games":{"minutes":63,"number":77,"position":"M","rating":"7.2","captain":false,"substitute":false},"offsides":null,"shots":{"total":1,"on":null},"goals":{"total":null,"conceded":0,"assists":null,"saves":null},"passes":{"total":25,"key":null,"accuracy":"20"},"tackles":{"total":3,"blocks":null,"interceptions":2},"duels":{"total":7,"won":5},"dribbles":{"attempts":1,"success":1,"past":null},"fouls":{"drawn":1,"committed":null},"cards":{"yellow":0,"red":0},"penalty":{"won":null,"commited":null,"scored":0,"missed":0,"saved":null}}]},{"player":{"id":30431,"name":"Andrea Colpani","photo":"https://media-4.api-sports.io/football/players/30431.png"},"statistics":[{"games":{"minutes":78,"number":28,"position":"F","rating":"6.9","captain":false,"substitute":false},"offsides":null,"shots":{"total":1,"on":null},"goals":{"total":null,"conceded":0,"assists":null,"saves":null},"passes":{"total":21,"key":2,"accuracy":"18"},"tackles":{"total":1,"blocks":null,"interceptions":1},"duels":{"total":7,"won":3},"dribbles":{"attempts":1,"success":null,"past":null},"fouls":{"drawn":2,"committed":null},"cards":{"yellow":0,"red":0},"penalty":{"won":null,"commited":null,"scored":0,"missed":0,"saved":null}}]},{"player":{"id":263481,"name":"Lorenzo Colombo","photo":"https://media-4.api-sports.io/football/players/263481.png"},"statistics":[{"games":{"minutes":78,"number":9,"position":"F","rating":"6.9","captain":false,"substitute":false},"offsides":null,"shots":{"total":1,"on":1},"goals":{"total":null,"conceded":0,"assists":null,"saves":null},"passes":{"total":22,"key":null,"accuracy":"15"},"tackles":{"total":1,"blocks":null,"interceptions":null},"duels":{"total":15,"won":5},"dribbles":{"attempts":1,"success":1,"past":1},"fouls":{"drawn":null,"committed":null},"cards":{"yellow":0,"red":0},"penalty":{"won":null,"commited":null,"scored":0,"missed":0,"saved":null}}]},{"player":{"id":30603,"name":"Dany Mota","photo":"https://media-4.api-sports.io/football/players/30603.png"},"statistics":[{"games":{"minutes":64,"number":47,"position":"F","rating":"6.9","captain":false,"substitute":false},"offsides":2,"shots":{"total":1,"on":1},"goals":{"total":null,"conceded":0,"assists":null,"saves":null},"passes":{"total":32,"key":2,"accuracy":"24"},"tackles":{"total":null,"blocks":null,"interceptions":null},"duels":{"total":7,"won":3},"dribbles":{"attempts":1,"success":null,"past":null},"fouls":{"drawn":1,"committed":null},"cards":{"yellow":0,"red":0},"penalty":{"won":null,"commited":null,"scored":0,"missed":0,"saved":null}}]},{"player":{"id":30708,"name":"Samuele Birindelli","photo":"https://media-4.api-sports.io/football/players/30708.png"},"statistics":[{"games":{"minutes":27,"number":19,"position":"D","rating":"6.6","captain":false,"substitute":true},"offsides":null,"shots":{"total":null,"on":null},"goals":{"total":null,"conceded":0,"assists":null,"saves":null},"passes":{"total":12,"key":1,"accuracy":"12"},"tackles":{"total":null,"blocks":null,"interceptions":null},"duels":{"total":3,"won":null},"dribbles":{"attempts":null,"success":null,"past":1},"fouls":{"drawn":null,"committed":2},"cards":{"yellow":1,"red":0},"penalty":{"won":null,"commited":null,"scored":0,"missed":0,"saved":null}}]},{"player":{"id":312985,"name":"Samuele Vignato","photo":"https://media-4.api-sports.io/football/players/312985.png"},"statistics":[{"games":{"minutes":26,"number":80,"position":"F","rating":"6.2","captain":false,"substitute":true},"offsides":null,"shots":{"total":1,"on":null},"goals":{"total":null,"conceded":0,"assists":null,"saves":null},"passes":{"total":11,"key":null,"accuracy":"7"},"tackles":{"total":null,"blocks":null,"interceptions":null},"duels":{"total":4,"won":1},"dribbles":{"attempts":null,"success":null,"past":1},"fouls":{"drawn":1,"committed":1},"cards":{"yellow":1,"red":0},"penalty":{"won":null,"commited":null,"scored":0,"missed":0,"saved":null}}]},{"player":{"id":46792,"name":"Pablo Marí","photo":"https://media-4.api-sports.io/football/players/46792.png"},"statistics":[{"games":{"minutes":23,"number":22,"position":"D","rating":"6.7","captain":false,"substitute":true},"offsides":null,"shots":{"total":null,"on":null},"goals":{"total":null,"conceded":0,"assists":null,"saves":null},"passes":{"total":13,"key":null,"accuracy":"13"},"tackles":{"total":null,"blocks":null,"interceptions":null},"duels":{"total":1,"won":1},"dribbles":{"attempts":null,"success":null,"past":null},"fouls":{"drawn":null,"committed":null},"cards":{"yellow":1,"red":0},"penalty":{"won":null,"commited":null,"scored":0,"missed":0,"saved":null}}]},{"player":{"id":31024,"name":"José Machín","photo":"https://media-4.api-sports.io/football/players/31024.png"},"statistics":[{"games":{"minutes":12,"number":7,"position":"M","rating":"6.9","captain":false,"substitute":true},"offsides":null,"shots":{"total":1,"on":null},"goals":{"total":null,"conceded":0,"assists":null,"saves":null},"passes":{"total":9,"key":null,"accuracy":"5"},"tackles":{"total":null,"blocks":null,"interceptions":null},"duels":{"total":1,"won":1},"dribbles":{"attempts":null,"success":null,"past":null},"fouls":{"drawn":1,"committed":null},"cards":{"yellow":0,"red":0},"penalty":{"won":null,"commited":null,"scored":0,"missed":0,"saved":null}}]},{"player":{"id":9072,"name":"Mirko Marić","photo":"https://media-4.api-sports.io/football/players/9072.png"},"statistics":[{"games":{"minutes":12,"number":24,"position":"F","rating":"6.5","captain":false,"substitute":true},"offsides":null,"shots":{"total":null,"on":null},"goals":{"total":null,"conceded":0,"assists":null,"saves":null},"passes":{"total":6,"key":null,"accuracy":"5"},"tackles":{"total":null,"blocks":null,"interceptions":null},"duels":{"total":4,"won":1},"dribbles":{"attempts":1,"success":null,"past":null},"fouls":{"drawn":null,"committed":null},"cards":{"yellow":0,"red":0},"penalty":{"won":null,"commited":null,"scored":0,"missed":0,"saved":null}}]},{"player":{"id":30704,"name":"Stefano Gori","photo":"https://media-4.api-sports.io/football/players/30704.png"},"statistics":[{"games":{"minutes":null,"number":66,"position":"G","rating":null,"captain":false,"substitute":true},"offsides":null,"shots":{"total":null,"on":null},"goals":{"total":null,"conceded":0,"assists":null,"saves":null},"passes":{"total":null,"key":null,"accuracy":null},"tackles":{"total":null,"blocks":null,"interceptions":null},"duels":{"total":null,"won":null},"dribbles":{"attempts":null,"success":null,"past":null},"fouls":{"drawn":null,"committed":null},"cards":{"yellow":0,"red":0},"penalty":{"won":null,"commited":null,"scored":0,"missed":0,"saved":null}}]},{"player":{"id":129553,"name":"Alessandro Sorrentino","photo":"https://media-4.api-sports.io/football/players/129553.png"},"statistics":[{"games":{"minutes":null,"number":23,"position":"G","rating":null,"captain":false,"substitute":true},"offsides":null,"shots":{"total":null,"on":null},"goals":{"total":null,"conceded":0,"assists":null,"saves":null},"passes":{"total":null,"key":null,"accuracy":null},"tackles":{"total":null,"blocks":null,"interceptions":null},"duels":{"total":null,"won":null},"dribbles":{"attempts":null,"success":null,"past":null},"fouls":{"drawn":null,"committed":null},"cards":{"yellow":0,"red":0},"penalty":{"won":null,"commited":null,"scored":0,"missed":0,"saved":null}}]},{"player":{"id":286473,"name":"Franco Carboni","photo":"https://media-4.api-sports.io/football/players/286473.png"},"statistics":[{"games":{"minutes":null,"number":11,"position":"D","rating":null,"captain":false,"substitute":true},"offsides":null,"shots":{"total":null,"on":null},"goals":{"total":null,"conceded":0,"assists":null,"saves":null},"passes":{"total":null,"key":null,"accuracy":null},"tackles":{"total":null,"blocks":null,"interceptions":null},"duels":{"total":null,"won":null},"dribbles":{"attempts":null,"success":null,"past":null},"fouls":{"drawn":null,"committed":null},"cards":{"yellow":0,"red":0},"penalty":{"won":null,"commited":null,"scored":0,"missed":0,"saved":null}}]},{"player":{"id":193,"name":"Danilo D'Ambrosio","photo":"https://media-4.api-sports.io/football/players/193.png"},"statistics":[{"games":{"minutes":null,"number":33,"position":"D","rating":null,"captain":false,"substitute":true},"offsides":null,"shots":{"total":null,"on":null},"goals":{"total":null,"conceded":0,"assists":null,"saves":null},"passes":{"total":null,"key":null,"accuracy":null},"tackles":{"total":null,"blocks":null,"interceptions":null},"duels":{"total":null,"won":null},"dribbles":{"attempts":null,"success":null,"past":null},"fouls":{"drawn":null,"committed":null},"cards":{"yellow":0,"red":0},"penalty":{"won":null,"commited":null,"scored":0,"missed":0,"saved":null}}]},{"player":{"id":162570,"name":"Giorgio Cittadini","photo":"https://media-4.api-sports.io/football/players/162570.png"},"statistics":[{"games":{"minutes":null,"number":46,"position":"D","rating":null,"captain":false,"substitute":true},"offsides":null,"shots":{"total":null,"on":null},"goals":{"total":null,"conceded":0,"assists":null,"saves":null},"passes":{"total":null,"key":null,"accuracy":null},"tackles":{"total":null,"blocks":null,"interceptions":null},"duels":{"total":null,"won":null},"dribbles":{"attempts":null,"success":null,"past":null},"fouls":{"drawn":null,"committed":null},"cards":{"yellow":0,"red":0},"penalty":{"won":null,"commited":null,"scored":0,"missed":0,"saved":null}}]},{"player":{"id":25911,"name":"Giulio Donati","photo":"https://media-4.api-sports.io/football/players/25911.png"},"statistics":[{"games":{"minutes":null,"number":2,"position":"D","rating":null,"captain":false,"substitute":true},"offsides":null,"shots":{"total":null,"on":null},"goals":{"total":null,"conceded":0,"assists":null,"saves":null},"passes":{"total":null,"key":null,"accuracy":null},"tackles":{"total":null,"blocks":null,"interceptions":null},"duels":{"total":null,"won":null},"dribbles":{"attempts":null,"success":null,"past":null},"fouls":{"drawn":null,"committed":null},"cards":{"yellow":0,"red":0},"penalty":{"won":null,"commited":null,"scored":0,"missed":0,"saved":null}}]},{"player":{"id":30768,"name":"Pedro Pereira","photo":"https://media-4.api-sports.io/football/players/30768.png"},"statistics":[{"games":{"minutes":null,"number":13,"position":"D","rating":null,"captain":false,"substitute":true},"offsides":null,"shots":{"total":null,"on":null},"goals":{"total":null,"conceded":0,"assists":null,"saves":null},"passes":{"total":null,"key":null,"accuracy":null},"tackles":{"total":null,"blocks":null,"interceptions":null},"duels":{"total":null,"won":null},"dribbles":{"attempts":null,"success":null,"past":null},"fouls":{"drawn":null,"committed":null},"cards":{"yellow":0,"red":0},"penalty":{"won":null,"commited":null,"scored":0,"missed":0,"saved":null}}]},{"player":{"id":266813,"name":"Warren Bondo","photo":"https://media-4.api-sports.io/football/players/266813.png"},"statistics":[{"games":{"minutes":null,"number":38,"position":"M","rating":null,"captain":false,"substitute":true},"offsides":null,"shots":{"total":null,"on":null},"goals":{"total":null,"conceded":0,"assists":null,"saves":null},"passes":{"total":null,"key":null,"accuracy":null},"tackles":{"total":null,"blocks":null,"interceptions":null},"duels":{"total":null,"won":null},"dribbles":{"attempts":null,"success":null,"past":null},"fouls":{"drawn":null,"committed":null},"cards":{"yellow":0,"red":0},"penalty":{"won":null,"commited":null,"scored":0,"missed":0,"saved":null}}]},{"player":{"id":341646,"name":"Valentín Carboni","photo":"https://media-4.api-sports.io/football/players/341646.png"},"statistics":[{"games":{"minutes":null,"number":21,"position":"M","rating":null,"captain":false,"substitute":true},"offsides":null,"shots":{"total":null,"on":null},"goals":{"total":null,"conceded":0,"assists":null,"saves":null},"passes":{"total":null,"key":null,"accuracy":null},"tackles":{"total":null,"blocks":null,"interceptions":null},"duels":{"total":null,"won":null},"dribbles":{"attempts":null,"success":null,"past":null},"fouls":{"drawn":null,"committed":null},"cards":{"yellow":0,"red":0},"penalty":{"won":null,"commited":null,"scored":0,"missed":0,"saved":null}}]},{"player":{"id":31678,"name":"Jean-Daniel Akpa Akpro","photo":"https://media-4.api-sports.io/football/players/31678.png"},"statistics":[{"games":{"minutes":null,"number":8,"position":"M","rating":null,"captain":false,"substitute":true},"offsides":null,"shots":{"total":null,"on":null},"goals":{"total":null,"conceded":0,"assists":null,"saves":null},"passes":{"total":null,"key":null,"accuracy":null},"tackles":{"total":null,"blocks":null,"interceptions":null},"duels":{"total":null,"won":null},"dribbles":{"attempts":null,"success":null,"past":null},"fouls":{"drawn":null,"committed":null},"cards":{"yellow":0,"red":0},"penalty":{"won":null,"commited":null,"scored":0,"missed":0,"saved":null}}]}]},{"team":{"id":500,"name":"Bologna","logo":"https://media-4.api-sports.io/football/teams/500.png","update":"2023-10-10T04:05:11+00:00"},"players":[{"player":{"id":2998,"name":"Łukasz Skorupski","photo":"https://media-4.api-sports.io/football/players/2998.png"},"statistics":[{"games":{"minutes":90,"number":28,"position":"G","rating":"7.7","captain":false,"substitute":false},"offsides":null,"shots":{"total":null,"on":null},"goals":{"total":null,"conceded":0,"assists":null,"saves":3},"passes":{"total":23,"key":null,"accuracy":"21"},"tackles":{"total":null,"blocks":null,"interceptions":null},"duels":{"total":null,"won":null},"dribbles":{"attempts":null,"success":null,"past":null},"fouls":{"drawn":null,"committed":null},"cards":{"yellow":0,"red":0},"penalty":{"won":null,"commited":null,"scored":0,"missed":0,"saved":0}}]},{"player":{"id":30498,"name":"Lorenzo De Silvestri","photo":"https://media-4.api-sports.io/football/players/30498.png"},"statistics":[{"games":{"minutes":59,"number":29,"position":"D","rating":"7","captain":true,"substitute":false},"offsides":null,"shots":{"total":null,"on":null},"goals":{"total":null,"conceded":0,"assists":null,"saves":null},"passes":{"total":58,"key":null,"accuracy":"48"},"tackles":{"total":null,"blocks":1,"interceptions":null},"duels":{"total":4,"won":3},"dribbles":{"attempts":null,"success":null,"past":null},"fouls":{"drawn":1,"committed":null},"cards":{"yellow":0,"red":0},"penalty":{"won":null,"commited":null,"scored":0,"missed":0,"saved":null}}]},{"player":{"id":37604,"name":"Sam Beukema","photo":"https://media-4.api-sports.io/football/players/37604.png"},"statistics":[{"games":{"minutes":90,"number":31,"position":"D","rating":"7.5","captain":false,"substitute":false},"offsides":null,"shots":{"total":1,"on":1},"goals":{"total":null,"conceded":0,"assists":null,"saves":null},"passes":{"total":63,"key":null,"accuracy":"58"},"tackles":{"total":2,"blocks":null,"interceptions":1},"duels":{"total":8,"won":7},"dribbles":{"attempts":null,"success":null,"past":null},"fouls":{"drawn":null,"committed":null},"cards":{"yellow":0,"red":0},"penalty":{"won":null,"commited":null,"scored":0,"missed":0,"saved":null}}]},{"player":{"id":157052,"name":"Riccardo Calafiori","photo":"https://media-4.api-sports.io/football/players/157052.png"},"statistics":[{"games":{"minutes":90,"number":33,"position":"D","rating":"7.3","captain":false,"substitute":false},"offsides":1,"shots":{"total":null,"on":null},"goals":{"total":null,"conceded":0,"assists":null,"saves":null},"passes":{"total":51,"key":null,"accuracy":"49"},"tackles":{"total":2,"blocks":null,"interceptions":2},"duels":{"total":9,"won":5},"dribbles":{"attempts":null,"success":null,"past":null},"fouls":{"drawn":null,"committed":2},"cards":{"yellow":0,"red":0},"penalty":{"won":null,"commited":null,"scored":0,"missed":0,"saved":null}}]},{"player":{"id":30553,"name":"Charalampos Lykogiannis","photo":"https://media-4.api-sports.io/football/players/30553.png"},"statistics":[{"games":{"minutes":59,"number":22,"position":"D","rating":"6.9","captain":false,"substitute":false},"offsides":1,"shots":{"total":null,"on":null},"goals":{"total":null,"conceded":0,"assists":null,"saves":null},"passes":{"total":30,"key":1,"accuracy":"26"},"tackles":{"total":null,"blocks":null,"interceptions":null},"duels":{"total":1,"won":null},"dribbles":{"attempts":null,"success":null,"past":null},"fouls":{"drawn":null,"committed":null},"cards":{"yellow":0,"red":0},"penalty":{"won":null,"commited":null,"scored":0,"missed":0,"saved":null}}]},{"player":{"id":951,"name":"Michel Aebischer","photo":"https://media-4.api-sports.io/football/players/951.png"},"statistics":[{"games":{"minutes":90,"number":20,"position":"M","rating":"6.9","captain":false,"substitute":false},"offsides":null,"shots":{"total":null,"on":null},"goals":{"total":null,"conceded":0,"assists":null,"saves":null},"passes":{"total":63,"key":null,"accuracy":"55"},"tackles":{"total":1,"blocks":null,"interceptions":1},"duels":{"total":10,"won":4},"dribbles":{"attempts":1,"success":null,"past":1},"fouls":{"drawn":1,"committed":1},"cards":{"yellow":0,"red":0},"penalty":{"won":null,"commited":null,"scored":0,"missed":0,"saved":null}}]},{"player":{"id":319919,"name":"Oussama El Azzouzi","photo":"https://media-4.api-sports.io/football/players/319919.png"},"statistics":[{"games":{"minutes":90,"number":17,"position":"M","rating":"7","captain":false,"substitute":false},"offsides":null,"shots":{"total":null,"on":null},"goals":{"total":null,"conceded":0,"assists":null,"saves":null},"passes":{"total":67,"key":null,"accuracy":"61"},"tackles":{"total":2,"blocks":1,"interceptions":1},"duels":{"total":9,"won":3},"dribbles":{"attempts":1,"success":null,"past":2},"fouls":{"drawn":null,"committed":1},"cards":{"yellow":0,"red":0},"penalty":{"won":null,"commited":null,"scored":0,"missed":0,"saved":null}}]},{"player":{"id":30488,"name":"Riccardo Orsolini","photo":"https://media-4.api-sports.io/football/players/30488.png"},"statistics":[{"games":{"minutes":59,"number":7,"position":"M","rating":"6.6","captain":false,"substitute":false},"offsides":null,"shots":{"total":1,"on":1},"goals":{"total":null,"conceded":0,"assists":null,"saves":null},"passes":{"total":18,"key":1,"accuracy":"13"},"tackles":{"total":null,"blocks":null,"interceptions":null},"duels":{"total":5,"won":1},"dribbles":{"attempts":null,"success":null,"past":1},"fouls":{"drawn":1,"committed":1},"cards":{"yellow":1,"red":0},"penalty":{"won":null,"commited":null,"scored":0,"missed":0,"saved":null}}]},{"player":{"id":44814,"name":"Lewis Ferguson","photo":"https://media-4.api-sports.io/football/players/44814.png"},"statistics":[{"games":{"minutes":90,"number":19,"position":"M","rating":"7.2","captain":false,"substitute":false},"offsides":null,"shots":{"total":1,"on":1},"goals":{"total":null,"conceded":0,"assists":null,"saves":null},"passes":{"total":56,"key":null,"accuracy":"49"},"tackles":{"total":3,"blocks":null,"interceptions":null},"duels":{"total":15,"won":7},"dribbles":{"attempts":2,"success":1,"past":null},"fouls":{"drawn":1,"committed":5},"cards":{"yellow":0,"red":0},"penalty":{"won":null,"commited":null,"scored":0,"missed":0,"saved":null}}]},{"player":{"id":48079,"name":"Jesper Karlsson","photo":"https://media-4.api-sports.io/football/players/48079.png"},"statistics":[{"games":{"minutes":59,"number":10,"position":"M","rating":"6.9","captain":false,"substitute":false},"offsides":null,"shots":{"total":null,"on":null},"goals":{"total":null,"conceded":0,"assists":null,"saves":null},"passes":{"total":22,"key":null,"accuracy":"17"},"tackles":{"total":1,"blocks":null,"interceptions":2},"duels":{"total":3,"won":2},"dribbles":{"attempts":2,"success":1,"past":null},"fouls":{"drawn":null,"committed":null},"cards":{"yellow":0,"red":0},"penalty":{"won":null,"commited":null,"scored":0,"missed":0,"saved":null}}]},{"player":{"id":70100,"name":"Joshua Zirkzee","photo":"https://media-4.api-sports.io/football/players/70100.png"},"statistics":[{"games":{"minutes":75,"number":9,"position":"F","rating":"7.2","captain":false,"substitute":false},"offsides":null,"shots":{"total":2,"on":2},"goals":{"total":null,"conceded":0,"assists":null,"saves":null},"passes":{"total":23,"key":1,"accuracy":"17"},"tackles":{"total":null,"blocks":null,"interceptions":null},"duels":{"total":6,"won":3},"dribbles":{"attempts":2,"success":1,"past":1},"fouls":{"drawn":null,"committed":1},"cards":{"yellow":0,"red":0},"penalty":{"won":null,"commited":null,"scored":0,"missed":0,"saved":null}}]},{"player":{"id":158710,"name":"Victor Kristiansen","photo":"https://media-4.api-sports.io/football/players/158710.png"},"statistics":[{"games":{"minutes":31,"number":15,"position":"M","rating":"6.7","captain":false,"substitute":true},"offsides":null,"shots":{"total":null,"on":null},"goals":{"total":null,"conceded":0,"assists":null,"saves":null},"passes":{"total":8,"key":null,"accuracy":"7"},"tackles":{"total":null,"blocks":null,"interceptions":null},"duels":{"total":1,"won":null},"dribbles":{"attempts":null,"success":null,"past":null},"fouls":{"drawn":null,"committed":1},"cards":{"yellow":0,"red":0},"penalty":{"won":null,"commited":null,"scored":0,"missed":0,"saved":null}}]},{"player":{"id":341974,"name":"Tommaso Corazza","photo":"https://media-4.api-sports.io/football/players/341974.png"},"statistics":[{"games":{"minutes":31,"number":16,"position":"D","rating":"6.7","captain":false,"substitute":true},"offsides":null,"shots":{"total":null,"on":null},"goals":{"total":null,"conceded":0,"assists":null,"saves":null},"passes":{"total":21,"key":null,"accuracy":"17"},"tackles":{"total":1,"blocks":null,"interceptions":2},"duels":{"total":2,"won":1},"dribbles":{"attempts":null,"success":null,"past":1},"fouls":{"drawn":null,"committed":null},"cards":{"yellow":0,"red":0},"penalty":{"won":null,"commited":null,"scored":0,"missed":0,"saved":null}}]},{"player":{"id":48648,"name":"Dan Ndoye","photo":"https://media-4.api-sports.io/football/players/48648.png"},"statistics":[{"games":{"minutes":31,"number":11,"position":"F","rating":"7","captain":false,"substitute":true},"offsides":null,"shots":{"total":null,"on":null},"goals":{"total":null,"conceded":0,"assists":null,"saves":null},"passes":{"total":9,"key":null,"accuracy":"5"},"tackles":{"total":null,"blocks":1,"interceptions":null},"duels":{"total":6,"won":4},"dribbles":{"attempts":2,"success":2,"past":null},"fouls":{"drawn":2,"committed":2},"cards":{"yellow":0,"red":0},"penalty":{"won":null,"commited":null,"scored":0,"missed":0,"saved":null}}]},{"player":{"id":1417,"name":"Alexis Saelemaekers","photo":"https://media-4.api-sports.io/football/players/1417.png"},"statistics":[{"games":{"minutes":27,"number":56,"position":"F","rating":"6.6","captain":false,"substitute":true},"offsides":null,"shots":{"total":null,"on":null},"goals":{"total":null,"conceded":0,"assists":null,"saves":null},"passes":{"total":12,"key":1,"accuracy":"10"},"tackles":{"total":null,"blocks":null,"interceptions":null},"duels":{"total":11,"won":7},"dribbles":{"attempts":7,"success":4,"past":null},"fouls":{"drawn":3,"committed":1},"cards":{"yellow":2,"red":1},"penalty":{"won":null,"commited":null,"scored":0,"missed":0,"saved":null}}]},{"player":{"id":38713,"name":"Sydney van Hooijdonk","photo":"https://media-4.api-sports.io/football/players/38713.png"},"statistics":[{"games":{"minutes":15,"number":77,"position":"F","rating":"6.7","captain":false,"substitute":true},"offsides":null,"shots":{"total":null,"on":null},"goals":{"total":null,"conceded":0,"assists":null,"saves":null},"passes":{"total":1,"key":null,"accuracy":"1"},"tackles":{"total":2,"blocks":null,"interceptions":null},"duels":{"total":3,"won":3},"dribbles":{"attempts":null,"success":null,"past":null},"fouls":{"drawn":null,"committed":null},"cards":{"yellow":0,"red":0},"penalty":{"won":null,"commited":null,"scored":0,"missed":0,"saved":null}}]},{"player":{"id":31098,"name":"Federico Ravaglia","photo":"https://media-4.api-sports.io/football/players/31098.png"},"statistics":[{"games":{"minutes":null,"number":34,"position":"G","rating":null,"captain":false,"substitute":true},"offsides":null,"shots":{"total":null,"on":null},"goals":{"total":null,"conceded":0,"assists":null,"saves":null},"passes":{"total":null,"key":null,"accuracy":null},"tackles":{"total":null,"blocks":null,"interceptions":null},"duels":{"total":null,"won":null},"dribbles":{"attempts":null,"success":null,"past":null},"fouls":{"drawn":null,"committed":null},"cards":{"yellow":0,"red":0},"penalty":{"won":null,"commited":null,"scored":0,"missed":0,"saved":null}}]},{"player":{"id":339180,"name":"Nicola Bagnolini","photo":"https://media-4.api-sports.io/football/players/339180.png"},"statistics":[{"games":{"minutes":null,"number":23,"position":"G","rating":null,"captain":false,"substitute":true},"offsides":null,"shots":{"total":null,"on":null},"goals":{"total":null,"conceded":0,"assists":null,"saves":null},"passes":{"total":null,"key":null,"accuracy":null},"tackles":{"total":null,"blocks":null,"interceptions":null},"duels":{"total":null,"won":null},"dribbles":{"attempts":null,"success":null,"past":null},"fouls":{"drawn":null,"committed":null},"cards":{"yellow":0,"red":0},"penalty":{"won":null,"commited":null,"scored":0,"missed":0,"saved":null}}]},{"player":{"id":30853,"name":"Kevin Bonifazi","photo":"https://media-4.api-sports.io/football/players/30853.png"},"statistics":[{"games":{"minutes":null,"number":14,"position":"D","rating":null,"captain":false,"substitute":true},"offsides":null,"shots":{"total":null,"on":null},"goals":{"total":null,"conceded":0,"assists":null,"saves":null},"passes":{"total":null,"key":null,"accuracy":null},"tackles":{"total":null,"blocks":null,"interceptions":null},"duels":{"total":null,"won":null},"dribbles":{"attempts":null,"success":null,"past":null},"fouls":{"drawn":null,"committed":null},"cards":{"yellow":0,"red":0},"penalty":{"won":null,"commited":null,"scored":0,"missed":0,"saved":null}}]},{"player":{"id":2807,"name":"Remo Freuler","photo":"https://media-4.api-sports.io/football/players/2807.png"},"statistics":[{"games":{"minutes":null,"number":8,"position":"M","rating":null,"captain":false,"substitute":true},"offsides":null,"shots":{"total":null,"on":null},"goals":{"total":null,"conceded":0,"assists":null,"saves":null},"passes":{"total":null,"key":null,"accuracy":null},"tackles":{"total":null,"blocks":null,"interceptions":null},"duels":{"total":null,"won":null},"dribbles":{"attempts":null,"success":null,"past":null},"fouls":{"drawn":null,"committed":null},"cards":{"yellow":0,"red":0},"penalty":{"won":null,"commited":null,"scored":0,"missed":0,"saved":null}}]},{"player":{"id":1322,"name":"Nikola Moro","photo":"https://media-4.api-sports.io/football/players/1322.png"},"statistics":[{"games":{"minutes":null,"number":6,"position":"M","rating":null,"captain":false,"substitute":true},"offsides":null,"shots":{"total":null,"on":null},"goals":{"total":null,"conceded":0,"assists":null,"saves":null},"passes":{"total":null,"key":null,"accuracy":null},"tackles":{"total":null,"blocks":null,"interceptions":null},"duels":{"total":null,"won":null},"dribbles":{"attempts":null,"success":null,"past":null},"fouls":{"drawn":null,"committed":null},"cards":{"yellow":0,"red":0},"penalty":{"won":null,"commited":null,"scored":0,"missed":0,"saved":null}}]},{"player":{"id":182280,"name":"Kacper Urbański","photo":"https://media-4.api-sports.io/football/players/182280.png"},"statistics":[{"games":{"minutes":null,"number":82,"position":"M","rating":null,"captain":false,"substitute":true},"offsides":null,"shots":{"total":null,"on":null},"goals":{"total":null,"conceded":0,"assists":null,"saves":null},"passes":{"total":null,"key":null,"accuracy":null},"tackles":{"total":null,"blocks":null,"interceptions":null},"duels":{"total":null,"won":null},"dribbles":{"attempts":null,"success":null,"past":null},"fouls":{"drawn":null,"committed":null},"cards":{"yellow":0,"red":0},"penalty":{"won":null,"commited":null,"scored":0,"missed":0,"saved":null}}]},{"player":{"id":322630,"name":"Giovanni Fabbian","photo":"https://media-4.api-sports.io/football/players/322630.png"},"statistics":[{"games":{"minutes":null,"number":80,"position":"M","rating":null,"captain":false,"substitute":true},"offsides":null,"shots":{"total":null,"on":null},"goals":{"total":null,"conceded":0,"assists":null,"saves":null},"passes":{"total":null,"key":null,"accuracy":null},"tackles":{"total":null,"blocks":null,"interceptions":null},"duels":{"total":null,"won":null},"dribbles":{"attempts":null,"success":null,"past":null},"fouls":{"drawn":null,"committed":null},"cards":{"yellow":0,"red":0},"penalty":{"won":null,"commited":null,"scored":0,"missed":0,"saved":null}}]}]}]}]